Mean_Squared_Error/__init__.py
Mean_Squared_Error/main.py
Mean_Squared_Error-0.4.0.dist-info/METADATA
Mean_Squared_Error-0.4.0.dist-info/WHEEL
Mean_Squared_Error-0.4.0.dist-info/top_level.txt
Mean_Squared_Error-0.4.0.dist-info/RECORD
