Metadata-Version: 2.1
Name: Mean_Squared_Error
Version: 0.4.0
